mercado_bitcoin/DataAPI.py
mercado_bitcoin/TradeAPI.py
mercado_bitcoin/__init__.py
mercado_bitcoin-1.0.1.dist-info/LICENSE
mercado_bitcoin-1.0.1.dist-info/METADATA
mercado_bitcoin-1.0.1.dist-info/WHEEL
mercado_bitcoin-1.0.1.dist-info/top_level.txt
mercado_bitcoin-1.0.1.dist-info/RECORD
