Metadata-Version: 2.1
Name: mercado-bitcoin
Version: 1.0.1
Summary: API Client in Python for Mercado Bitcoin
Home-page: https://github.com/mbampi/mercado-bitcoin
Author: Matheus Dussin Bampi
Author-email: matheusbampi@gmail.com
License: UNKNOWN
Download-URL: https://github.com/mbampi/mercado-bitcoin/archive/v1.0.1.tar.gz
Keywords: bitcoin,trade,data,finance,crypto,criptomoedas,mercadobitcoin
Platform: UNKNOWN
Classifier: Development Status :: 4 - Beta
Classifier: Intended Audience :: Developers
Classifier: Programming Language :: Python :: 3
Classifier: License :: OSI Approved :: MIT License
Classifier: Operating System :: OS Independent
Requires-Python: >=3.6
Requires-Dist: requests
Requires-Dist: urllib3
